topsis/__init__.py
topsis/topsis.py
topsis_akshitdhiman_102303336-1.0.0.dist-info/METADATA
topsis_akshitdhiman_102303336-1.0.0.dist-info/WHEEL
topsis_akshitdhiman_102303336-1.0.0.dist-info/entry_points.txt
topsis_akshitdhiman_102303336-1.0.0.dist-info/top_level.txt
topsis_akshitdhiman_102303336-1.0.0.dist-info/RECORD
