Metadata-Version: 2.1
Name: topsis-akshitdhiman-102303336
Version: 1.0.0
Summary: TOPSIS implementation using Python
Author: Akshit Dhiman
Requires-Dist: pandas
Requires-Dist: numpy
